odoo/addons/l10n_es_aeat_mod347_igic/README.rst
odoo/addons/l10n_es_aeat_mod347_igic/__init__.py
odoo/addons/l10n_es_aeat_mod347_igic/__manifest__.py
odoo/addons/l10n_es_aeat_mod347_igic/data/tax_code_map_mod347_igic_data.xml
odoo/addons/l10n_es_aeat_mod347_igic/i18n/l10n_es_aeat_mod347_igic.pot
odoo/addons/l10n_es_aeat_mod347_igic/readme/CONTRIBUTORS.rst
odoo/addons/l10n_es_aeat_mod347_igic/readme/DESCRIPTION.rst
odoo/addons/l10n_es_aeat_mod347_igic/readme/INSTALL.rst
odoo/addons/l10n_es_aeat_mod347_igic/static/description/icon.png
odoo/addons/l10n_es_aeat_mod347_igic/static/description/index.html
odoo_addon_l10n_es_aeat_mod347_igic-16.0.1.0.2.dist-info/METADATA
odoo_addon_l10n_es_aeat_mod347_igic-16.0.1.0.2.dist-info/WHEEL
odoo_addon_l10n_es_aeat_mod347_igic-16.0.1.0.2.dist-info/top_level.txt
odoo_addon_l10n_es_aeat_mod347_igic-16.0.1.0.2.dist-info/RECORD
