Metadata-Version: 2.1
Name: odoo-addon-l10n_es_aeat_mod347_igic
Version: 16.0.1.0.2
Summary: AEAT modelo 347 IGIC
Home-page: https://github.com/OCA/l10n-spain
Author: Binhex System Solutions,Odoo Community Association (OCA)
Author-email: support@odoo-community.org
License: AGPL-3
Classifier: Programming Language :: Python
Classifier: Framework :: Odoo
Classifier: Framework :: Odoo :: 16.0
Classifier: License :: OSI Approved :: GNU Affero General Public License v3
Requires-Python: >=3.10
Requires-Dist: odoo-addon-l10n-es-aeat-mod347<16.1dev,>=16.0dev
Requires-Dist: odoo-addon-l10n-es-igic<16.1dev,>=16.0dev
Requires-Dist: odoo<16.1dev,>=16.0a
